Simulation/lfsr.v
`timescale 1ns / 1ps

// LFSR Core Module
module LFSR_core(
    input clk,
    input rst,        // active-high reset
    input enable,
    input [7:0] seed,
    input load,
    input [7:0] taps,
    output reg [7:0] lfsr_out
);
    
    wire feedback;
    wire lfsr_stuck_zero;
    
    assign feedback = ^(lfsr_out & taps);
    assign lfsr_stuck_zero = (lfsr_out == 8'b00000000);
    
    always @(posedge clk) begin
        if (rst) begin
            lfsr_out <= 8'h19;  // Default seed 0x19
        end
        else if (load) begin
            lfsr_out <= seed;    // Load new seed
        end
        else if (enable) begin
            if (lfsr_stuck_zero) begin
                lfsr_out <= 8'h19;  // Recovery from stuck-at-zero
            end
            else begin
                lfsr_out <= {lfsr_out[6:0], feedback};  // Shift left with feedback
            end
        end
        // If neither load nor enable, hold current value
    end
    
endmodule

// AXI-Lite Slave Module
module lfsr_axi_slave #(
    parameter ADDR_WIDTH = 4,
    parameter DATA_WIDTH = 8
)(
    input clk,
    input resetn,  // active-low reset
   
    // Write Address Channel
    input  [ADDR_WIDTH-1:0] s_axi_awaddr,
    input                   s_axi_awvalid,
    output reg              s_axi_awready,
   
    // Write Data Channel
    input  [DATA_WIDTH-1:0] s_axi_wdata,
    input                   s_axi_wvalid,
    output reg              s_axi_wready,
    
    // Write Response Channel
    output reg [1:0]        s_axi_bresp,
    output reg              s_axi_bvalid,
    input                   s_axi_bready,
    
    // Read Address Channel
    input  [ADDR_WIDTH-1:0] s_axi_araddr,
    input                   s_axi_arvalid,
    output reg              s_axi_arready,
   
    // Read Data Channel
    output reg [DATA_WIDTH-1:0] s_axi_rdata,
    output reg              s_axi_rvalid,
    input                   s_axi_rready,
    
    // Register interface
    output reg [7:0] ctrl_reg,
    output reg [7:0] seed_reg,
    output reg [7:0] taps_reg,
    input  [7:0]     lfsr_data
);

    // AXI Write State Machine
    localparam WRITE_IDLE  = 2'b00,
               WRITE_DATA  = 2'b01,
               WRITE_RESP  = 2'b10;
    
    reg [1:0] write_state;
    reg [ADDR_WIDTH-1:0] write_addr;
    
    // AXI Read State Machine  
    localparam READ_IDLE = 1'b0,
               READ_DATA = 1'b1;
    
    reg read_state;

    // Write Channel Logic
    always @(posedge clk) begin
        if (!resetn) begin
            write_state   <= WRITE_IDLE;
            s_axi_awready <= 1'b0;
            s_axi_wready  <= 1'b0;
            s_axi_bvalid  <= 1'b0;
            s_axi_bresp   <= 2'b00;
            write_addr    <= 0;
            ctrl_reg      <= 8'h00;
            seed_reg      <= 8'h00;
            taps_reg      <= 8'h00;
        end else begin
            case (write_state)
                WRITE_IDLE: begin
                    s_axi_awready <= 1'b1;
                    s_axi_wready  <= 1'b1;
                    s_axi_bvalid  <= 1'b0;
                    
                    if (s_axi_awvalid && s_axi_wvalid) begin
                        write_addr    <= s_axi_awaddr;
                        s_axi_awready <= 1'b0;
                        s_axi_wready  <= 1'b0;
                        write_state   <= WRITE_DATA;
                    end
                end
                
                WRITE_DATA: begin
                    // Perform the write
                    case (write_addr[3:0])
                        4'h0: begin 
                            ctrl_reg <= s_axi_wdata;
                            s_axi_bresp <= 2'b00; // OK
                        end
                        4'h4: begin 
                            seed_reg <= s_axi_wdata;
                            s_axi_bresp <= 2'b00; // OK
                        end
                        4'h8: begin 
                            taps_reg <= s_axi_wdata;
                            s_axi_bresp <= 2'b00; // OK
                        end
                        default: begin
                            s_axi_bresp <= 2'b10; // SLVERR
                        end
                    endcase
                    
                    s_axi_bvalid <= 1'b1;
                    write_state  <= WRITE_RESP;
                end
                
                WRITE_RESP: begin
                    if (s_axi_bready) begin
                        s_axi_bvalid <= 1'b0;
                        write_state  <= WRITE_IDLE;
                    end
                end
                
                default: write_state <= WRITE_IDLE;
            endcase
        end
    end

    // Read Channel Logic
    always @(posedge clk) begin
        if (!resetn) begin
            read_state    <= READ_IDLE;
            s_axi_arready <= 1'b0;
            s_axi_rvalid  <= 1'b0;
            s_axi_rdata   <= 8'h00;
        end else begin
            case (read_state)
                READ_IDLE: begin
                    s_axi_arready <= 1'b1;
                    s_axi_rvalid  <= 1'b0;
                    
                    if (s_axi_arvalid) begin
                        s_axi_arready <= 1'b0;
                        
                        // Decode address and provide data
                        case (s_axi_araddr[3:0])
                            4'h0: s_axi_rdata <= ctrl_reg;
                            4'h4: s_axi_rdata <= seed_reg;
                            4'h8: s_axi_rdata <= taps_reg;
                            4'hC: s_axi_rdata <= lfsr_data;
                            default: s_axi_rdata <= 8'h00;
                        endcase
                        
                        s_axi_rvalid <= 1'b1;
                        read_state   <= READ_DATA;
                    end
                end
                
                READ_DATA: begin
                    if (s_axi_rready) begin
                        s_axi_rvalid <= 1'b0;
                        read_state   <= READ_IDLE;
                    end
                end
                
                default: read_state <= READ_IDLE;
            endcase
        end
    end

endmodule

// Top Module
module lfsr_axi_top #(
    parameter ADDR_WIDTH = 4,
    parameter DATA_WIDTH = 8
)(
    input clk,
    input resetslave,  // active-low reset
    
    // AXI-Lite Slave Interface
    input  [ADDR_WIDTH-1:0] s_axi_awaddr,
    input                   s_axi_awvalid,
    output                  s_axi_awready,
    input  [DATA_WIDTH-1:0] s_axi_wdata,
    input                   s_axi_wvalid,
    output                  s_axi_wready,
    output [1:0]            s_axi_bresp,
    output                  s_axi_bvalid,
    input                   s_axi_bready,
    
    input  [ADDR_WIDTH-1:0] s_axi_araddr,
    input                   s_axi_arvalid,
    output                  s_axi_arready,
    output [DATA_WIDTH-1:0] s_axi_rdata,
    output                  s_axi_rvalid,
    input                   s_axi_rready
);
    
    // Internal signals
    wire [7:0] ctrl_reg, seed_reg, taps_reg, lfsr_out;
    wire enable, load, rst_lfsr;
    
    // Extract control signals
    assign enable = ctrl_reg[0];
    assign load   = ctrl_reg[1];
    assign rst_lfsr = ~resetslave;  // Convert to active-high
    
    // Instantiate AXI-Lite slave
    lfsr_axi_slave #(
        .ADDR_WIDTH(ADDR_WIDTH),
        .DATA_WIDTH(DATA_WIDTH)
    ) u_axi_slave (
        .clk(clk),
        .resetn(resetslave),
        .s_axi_awaddr(s_axi_awaddr),
        .s_axi_awvalid(s_axi_awvalid),
        .s_axi_awready(s_axi_awready),
        .s_axi_wdata(s_axi_wdata),
        .s_axi_wvalid(s_axi_wvalid),
        .s_axi_wready(s_axi_wready),
        .s_axi_bresp(s_axi_bresp),
        .s_axi_bvalid(s_axi_bvalid),
        .s_axi_bready(s_axi_bready),
        .s_axi_araddr(s_axi_araddr),
        .s_axi_arvalid(s_axi_arvalid),
        .s_axi_arready(s_axi_arready),
        .s_axi_rdata(s_axi_rdata),
        .s_axi_rvalid(s_axi_rvalid),
        .s_axi_rready(s_axi_rready),
        .ctrl_reg(ctrl_reg),
        .seed_reg(seed_reg),
        .taps_reg(taps_reg),
        .lfsr_data(lfsr_out)
    );
    
    // Instantiate LFSR core
    LFSR_core u_lfsr (
        .clk(clk),
        .rst(rst_lfsr),
        .enable(enable),
        .load(load),
        .seed(seed_reg),
        .taps(taps_reg),
        .lfsr_out(lfsr_out)
    );
    
endmodule



// CocoTB Testbench - Only DUT instantiation
module tb_lfsr_axi_cocotb;

    parameter ADDR_WIDTH = 4;
    parameter DATA_WIDTH = 8;

    reg clk;
    reg resetslave;

    // AXI signals
    reg  [ADDR_WIDTH-1:0] s_axi_awaddr;
    reg                   s_axi_awvalid;
    wire                  s_axi_awready;

    reg                   s_axi_wvalid;
    reg  [DATA_WIDTH-1:0] s_axi_wdata;
    wire                  s_axi_wready;

    wire                  s_axi_bvalid;
    reg                   s_axi_bready;
    wire [1:0]            s_axi_bresp;

    reg  [ADDR_WIDTH-1:0] s_axi_araddr;
    reg                   s_axi_arvalid;
    wire                  s_axi_arready;

    wire                  s_axi_rvalid;
    reg                   s_axi_rready;
    wire [DATA_WIDTH-1:0] s_axi_rdata;

    // DUT instantiation
    lfsr_axi_top #(
        .ADDR_WIDTH(ADDR_WIDTH),
        .DATA_WIDTH(DATA_WIDTH)
    ) dut (
        .clk(clk),
        .resetslave(resetslave),
        .s_axi_awaddr(s_axi_awaddr),
        .s_axi_awvalid(s_axi_awvalid),
        .s_axi_awready(s_axi_awready),
        .s_axi_wvalid(s_axi_wvalid),
        .s_axi_wdata(s_axi_wdata),
        .s_axi_wready(s_axi_wready),
        .s_axi_bready(s_axi_bready),
        .s_axi_bvalid(s_axi_bvalid),
        .s_axi_bresp(s_axi_bresp),
        .s_axi_araddr(s_axi_araddr),
        .s_axi_arvalid(s_axi_arvalid),
        .s_axi_arready(s_axi_arready),
        .s_axi_rready(s_axi_rready),
        .s_axi_rvalid(s_axi_rvalid),
        .s_axi_rdata(s_axi_rdata)
    );

    // Clock generation for CocoTB
    initial begin
        clk = 0;
        forever #5 clk = ~clk;
    end

    // VCD dump for debugging
    initial begin
        $dumpfile("tb_lfsr_axi_cocotb.vcd");
        $dumpvars(0, tb_lfsr_axi_cocotb);
    end

endmodule

Simulation/tb_lfsr_axi_cocotb.vcd
$date
	Wed Jun 25 14:31:45 2025
$end
$version
	Icarus Verilog
$end
$timescale
	1ps
$end
$scope module tb_lfsr_axi_cocotb $end
$var wire 1 ! s_axi_wready $end
$var wire 1 " s_axi_rvalid $end
$var wire 8 # s_axi_rdata [7:0] $end
$var wire 1 $ s_axi_bvalid $end
$var wire 2 % s_axi_bresp [1:0] $end
$var wire 1 & s_axi_awready $end
$var wire 1 ' s_axi_arready $end
$var parameter 32 ( ADDR_WIDTH $end
$var parameter 32 ) DATA_WIDTH $end
$var reg 1 * clk $end
$var reg 1 + resetslave $end
$var reg 4 , s_axi_araddr [3:0] $end
$var reg 1 - s_axi_arvalid $end
$var reg 4 . s_axi_awaddr [3:0] $end
$var reg 1 / s_axi_awvalid $end
$var reg 1 0 s_axi_bready $end
$var reg 1 1 s_axi_rready $end
$var reg 8 2 s_axi_wdata [7:0] $end
$var reg 1 3 s_axi_wvalid $end
$scope module dut $end
$var wire 1 * clk $end
$var wire 1 + resetslave $end
$var wire 1 4 rst_lfsr $end
$var wire 4 5 s_axi_araddr [3:0] $end
$var wire 1 - s_axi_arvalid $end
$var wire 4 6 s_axi_awaddr [3:0] $end
$var wire 1 / s_axi_awvalid $end
$var wire 1 0 s_axi_bready $end
$var wire 1 1 s_axi_rready $end
$var wire 8 7 s_axi_wdata [7:0] $end
$var wire 1 3 s_axi_wvalid $end
$var wire 8 8 taps_reg [7:0] $end
$var wire 8 9 seed_reg [7:0] $end
$var wire 1 ! s_axi_wready $end
$var wire 1 " s_axi_rvalid $end
$var wire 8 : s_axi_rdata [7:0] $end
$var wire 1 $ s_axi_bvalid $end
$var wire 2 ; s_axi_bresp [1:0] $end
$var wire 1 & s_axi_awready $end
$var wire 1 ' s_axi_arready $end
$var wire 1 < load $end
$var wire 8 = lfsr_out [7:0] $end
$var wire 1 > enable $end
$var wire 8 ? ctrl_reg [7:0] $end
$var parameter 32 @ ADDR_WIDTH $end
$var parameter 32 A DATA_WIDTH $end
$scope module u_axi_slave $end
$var wire 1 * clk $end
$var wire 1 + resetn $end
$var wire 4 B s_axi_araddr [3:0] $end
$var wire 1 - s_axi_arvalid $end
$var wire 4 C s_axi_awaddr [3:0] $end
$var wire 1 / s_axi_awvalid $end
$var wire 1 0 s_axi_bready $end
$var wire 1 1 s_axi_rready $end
$var wire 8 D s_axi_wdata [7:0] $end
$var wire 1 3 s_axi_wvalid $end
$var wire 8 E lfsr_data [7:0] $end
$var parameter 32 F ADDR_WIDTH $end
$var parameter 32 G DATA_WIDTH $end
$var parameter 1 H READ_DATA $end
$var parameter 1 I READ_IDLE $end
$var parameter 2 J WRITE_DATA $end
$var parameter 2 K WRITE_IDLE $end
$var parameter 2 L WRITE_RESP $end
$var reg 8 M ctrl_reg [7:0] $end
$var reg 1 N read_state $end
$var reg 1 ' s_axi_arready $end
$var reg 1 & s_axi_awready $end
$var reg 2 O s_axi_bresp [1:0] $end
$var reg 1 $ s_axi_bvalid $end
$var reg 8 P s_axi_rdata [7:0] $end
$var reg 1 " s_axi_rvalid $end
$var reg 1 ! s_axi_wready $end
$var reg 8 Q seed_reg [7:0] $end
$var reg 8 R taps_reg [7:0] $end
$var reg 4 S write_addr [3:0] $end
$var reg 2 T write_state [1:0] $end
$upscope $end
$scope module u_lfsr $end
$var wire 1 * clk $end
$var wire 1 > enable $end
$var wire 1 < load $end
$var wire 1 4 rst $end
$var wire 8 U seed [7:0] $end
$var wire 8 V taps [7:0] $end
$var wire 1 W lfsr_stuck_zero $end
$var wire 1 X feedback $end
$var reg 8 Y lfsr_out [7:0] $end
$upscope $end
$upscope $end
$upscope $end
$enddefinitions $end
$comment Show the parameter values. $end
$dumpall
b10 L
b0 K
b1 J
0I
1H
b1000 G
b100 F
b1000 A
b100 @
b1000 )
b100 (
$end
#0
$dumpvars
b11001 Y
0X
0W
b0 V
b0 U
b0 T
b0 S
b0 R
b0 Q
b0 P
b0 O
0N
b0 M
b11001 E
b0 D
b0 C
b0 B
b0 ?
0>
b11001 =
0<
b0 ;
b0 :
b0 9
b0 8
b0 7
b0 6
b0 5
14
03
b0 2
01
00
0/
b0 .
0-
b0 ,
0+
1*
0'
0&
b0 %
0$
b0 #
0"
0!
$end
#5000
0*
#10000
1*
#15000
0*
#20000
04
1+
1*
#25000
0*
#30000
1'
1!
1&
1*
#35000
0*
#40000
1*
#45000
0*
#50000
10
13
1/
1*
#55000
0*
#60000
03
0/
b1 T
0!
0&
1*
#65000
0*
#70000
b10 T
1$
1*
#75000
0*
#80000
b0 T
0$
1*
#85000
0*
#90000
00
1!
1&
1*
#95000
0*
#100000
10
13
b10100101 2
b10100101 7
b10100101 D
1/
b100 .
b100 6
b100 C
1*
#105000
0*
#110000
03
0/
b1 T
0!
0&
b100 S
1*
#115000
0*
#120000
b10 T
1$
b10100101 9
b10100101 Q
b10100101 U
1*
#125000
0*
#130000
b0 T
0$
1*
#135000
0*
#140000
00
1!
1&
1*
#145000
0*
#150000
10
13
b10110100 2
b10110100 7
b10110100 D
1/
b1000 .
b1000 6
b1000 C
1*
#155000
0*
#160000
03
0/
b1 T
0!
0&
b1000 S
1*
#165000
0*
#170000
1X
b10 T
1$
b10110100 8
b10110100 R
b10110100 V
1*
#175000
0*
#180000
b0 T
0$
1*
#185000
0*
#190000
00
1!
1&
1*
#195000
0*
#200000
11
1-
1*
#205000
0*
#210000
0-
1N
1"
0'
1*
#215000
0*
#220000
0N
0"
1*
#225000
0*
#230000
01
1'
1*
#235000
0*
#240000
11
1-
b100 ,
b100 5
b100 B
1*
#245000
0*
#250000
0-
1N
1"
b10100101 #
b10100101 :
b10100101 P
0'
1*
#255000
0*
#260000
0N
0"
1*
#265000
0*
#270000
01
1'
1*
#275000
0*
#280000
11
1-
b1000 ,
b1000 5
b1000 B
1*
#285000
0*
#290000
0-
1N
1"
b10110100 #
b10110100 :
b10110100 P
0'
1*
#295000
0*
#300000
0N
0"
1*
#305000
0*
#310000
1'
1*
#310001
14
0+
01
b0 ,
b0 5
b0 B
b0 2
b0 7
b0 D
b0 .
b0 6
b0 C
#315000
0*
#320000
0X
b0 8
b0 R
b0 V
b0 9
b0 Q
b0 U
b0 S
0!
0&
b0 #
b0 :
b0 P
0'
1*
#325000
0*
#330000
1*
#330001
04
1+
#335000
0*
#340000
1!
1&
1'
1*
#345000
0*
#350000
1*
#355000
0*
#360000
1*
#365000
0*
#370000
10
13
b10100101 2
b10100101 7
b10100101 D
1/
b100 .
b100 6
b100 C
1*
#375000
0*
#380000
03
0/
b1 T
0!
0&
b100 S
1*
#385000
0*
#390000
b10 T
1$
b10100101 9
b10100101 Q
b10100101 U
1*
#395000
0*
#400000
b0 T
0$
1*
#405000
0*
#410000
00
1!
1&
1*
#415000
0*
#420000
10
13
b10110100 2
b10110100 7
b10110100 D
1/
b1000 .
b1000 6
b1000 C
1*
#425000
0*
#430000
03
0/
b1 T
0!
0&
b1000 S
1*
#435000
0*
#440000
1X
b10 T
1$
b10110100 8
b10110100 R
b10110100 V
1*
#445000
0*
#450000
b0 T
0$
1*
#455000
0*
#460000
00
1!
1&
1*
#465000
0*
#470000
10
13
b10 2
b10 7
b10 D
1/
b0 .
b0 6
b0 C
1*
#475000
0*
#480000
03
0/
b1 T
0!
0&
b0 S
1*
#485000
0*
#490000
1<
b10 T
1$
b10 ?
b10 M
1*
#495000
0*
#500000
b0 T
0$
b10100101 =
b10100101 E
b10100101 Y
1*
#505000
0*
#510000
00
1!
1&
1*
#515000
0*
#520000
1*
#525000
0*
#530000
1*
#535000
0*
#540000
10
13
b0 2
b0 7
b0 D
1/
1*
#545000
0*
#550000
03
0/
b1 T
0!
0&
1*
#555000
0*
#560000
0<
b10 T
1$
b0 ?
b0 M
1*
#565000
0*
#570000
b0 T
0$
1*
#575000
0*
#580000
00
1!
1&
1*
#585000
0*
#590000
11
1-
b1100 ,
b1100 5
b1100 B
1*
#595000
0*
#600000
0-
1N
1"
b10100101 #
b10100101 :
b10100101 P
0'
1*
#605000
0*
#610000
0N
0"
1*
#615000
0*
#620000
1'
1*
#620001
14
0+
01
b0 ,
b0 5
b0 B
#625000
0*
#630000
0X
b11001 =
b11001 E
b11001 Y
b0 #
b0 :
b0 P
0'
b0 8
b0 R
b0 V
b0 9
b0 Q
b0 U
0!
0&
1*
#635000
0*
#640000
1*
#640001
04
1+
#645000
0*
#650000
1'
1!
1&
1*
#655000
0*
#660000
1*
#665000
0*
#670000
1*
#675000
0*
#680000
10
13
b10100101 2
b10100101 7
b10100101 D
1/
b100 .
b100 6
b100 C
1*
#685000
0*
#690000
03
0/
b1 T
0!
0&
b100 S
1*
#695000
0*
#700000
b10 T
1$
b10100101 9
b10100101 Q
b10100101 U
1*
#705000
0*
#710000
b0 T
0$
1*
#715000
0*
#720000
00
1!
1&
1*
#725000
0*
#730000
10
13
b10110100 2
b10110100 7
b10110100 D
1/
b1000 .
b1000 6
b1000 C
1*
#735000
0*
#740000
03
0/
b1 T
0!
0&
b1000 S
1*
#745000
0*
#750000
1X
b10 T
1$
b10110100 8
b10110100 R
b10110100 V
1*
#755000
0*
#760000
b0 T
0$
1*
#765000
0*
#770000
00
1!
1&
1*
#775000
0*
#780000
10
13
b10 2
b10 7
b10 D
1/
b0 .
b0 6
b0 C
1*
#785000
0*
#790000
03
0/
b1 T
0!
0&
b0 S
1*
#795000
0*
#800000
1<
b10 T
1$
b10 ?
b10 M
1*
#805000
0*
#810000
b10100101 =
b10100101 E
b10100101 Y
b0 T
0$
1*
#815000
0*
#820000
00
1!
1&
1*
#825000
0*
#830000
1*
#835000
0*
#840000
1*
#845000
0*
#850000
10
13
b1 2
b1 7
b1 D
1/
1*
#855000
0*
#860000
03
0/
b1 T
0!
0&
1*
#865000
0*
#870000
0<
1>
b10 T
1$
b1 ?
b1 M
1*
#875000
0*
#880000
0X
b0 T
0$
b1001011 =
b1001011 E
b1001011 Y
1*
#885000
0*
#890000
00
1X
b10010110 =
b10010110 E
b10010110 Y
1!
1&
1*
#895000
0*
#900000
0X
b101101 =
b101101 E
b101101 Y
1*
#905000
0*
#910000
1X
b1011010 =
b1011010 E
b1011010 Y
1*
#915000
0*
#920000
11
1-
b1100 ,
b1100 5
b1100 B
0X
b10110101 =
b10110101 E
b10110101 Y
1*
#925000
0*
#930000
0-
1X
b1101010 =
b1101010 E
b1101010 Y
1N
1"
b10110101 #
b10110101 :
b10110101 P
0'
1*
#935000
0*
#940000
0N
0"
b11010101 =
b11010101 E
b11010101 Y
1*
#945000
0*
#950000
01
0X
b10101011 =
b10101011 E
b10101011 Y
1'
1*
#955000
0*
#960000
b1010110 =
b1010110 E
b1010110 Y
1*
#965000
0*
#970000
1X
b10101100 =
b10101100 E
b10101100 Y
1*
#975000
0*
#980000
11
1-
b1011001 =
b1011001 E
b1011001 Y
1*
#985000
0*
#990000
0-
b10110011 =
b10110011 E
b10110011 Y
1N
1"
b1011001 #
b1011001 :
b1011001 P
0'
1*
#995000
0*
#1000000
0X
0N
0"
b1100111 =
b1100111 E
b1100111 Y
1*
#1005000
0*
#1010000
01
b11001110 =
b11001110 E
b11001110 Y
1'
1*
#1015000
0*
#1020000
1X
b10011100 =
b10011100 E
b10011100 Y
1*
#1025000
0*
#1030000
0X
b111001 =
b111001 E
b111001 Y
1*
#1035000
0*
#1040000
11
1-
b1110010 =
b1110010 E
b1110010 Y
1*
#1045000
0*
#1050000
0-
1X
b11100100 =
b11100100 E
b11100100 Y
1N
1"
b1110010 #
b1110010 :
b1110010 P
0'
1*
#1055000
0*
#1060000
0N
0"
b11001001 =
b11001001 E
b11001001 Y
1*
#1065000
0*
#1070000
01
0X
b10010011 =
b10010011 E
b10010011 Y
1'
1*
#1075000
0*
#1080000
b100110 =
b100110 E
b100110 Y
1*
#1085000
0*
#1090000
1X
b1001100 =
b1001100 E
b1001100 Y
1*
#1095000
0*
#1100000
11
1-
0X
b10011001 =
b10011001 E
b10011001 Y
1*
#1105000
0*
#1110000
0-
b110010 =
b110010 E
b110010 Y
1N
1"
b10011001 #
b10011001 :
b10011001 P
0'
1*
#1115000
0*
#1120000
0N
0"
b1100100 =
b1100100 E
b1100100 Y
1*
#1125000
0*
#1130000
01
1X
b11001000 =
b11001000 E
b11001000 Y
1'
1*
#1135000
0*
#1140000
0X
b10010001 =
b10010001 E
b10010001 Y
1*
#1145000
0*
#1150000
1X
b100010 =
b100010 E
b100010 Y
1*
#1155000
0*
#1160000
11
1-
b1000101 =
b1000101 E
b1000101 Y
1*
#1165000
0*
#1170000
0-
b10001011 =
b10001011 E
b10001011 Y
1N
1"
b1000101 #
b1000101 :
b1000101 P
0'
1*
#1175000
0*
#1180000
0X
0N
0"
b10111 =
b10111 E
b10111 Y
1*
#1185000
0*
#1190000
01
b101110 =
b101110 E
b101110 Y
1'
1*
#1195000
0*
#1200000
b1011100 =
b1011100 E
b1011100 Y
1*
#1205000
0*
#1210000
1X
b10111000 =
b10111000 E
b10111000 Y
1*
#1215000
0*
#1220000
11
1-
0X
b1110001 =
b1110001 E
b1110001 Y
1*
#1225000
0*
#1230000
0-
b11100010 =
b11100010 E
b11100010 Y
1N
1"
b1110001 #
b1110001 :
b1110001 P
0'
1*
#1235000
0*
#1240000
0N
0"
b11000100 =
b11000100 E
b11000100 Y
1*
#1245000
0*
#1250000
01
1X
b10001000 =
b10001000 E
b10001000 Y
1'
1*
#1255000
0*
#1260000
b10001 =
b10001 E
b10001 Y
1*
#1265000
0*
#1270000
b100011 =
b100011 E
b100011 Y
1*
#1275000
0*
#1280000
11
1-
b1000111 =
b1000111 E
b1000111 Y
1*
#1285000
0*
#1290000
0-
0X
b10001111 =
b10001111 E
b10001111 Y
1N
1"
b1000111 #
b1000111 :
b1000111 P
0'
1*
#1295000
0*
#1300000
0N
0"
b11110 =
b11110 E
b11110 Y
1*
#1305000
0*
#1310000
01
1X
b111100 =
b111100 E
b111100 Y
1'
1*
#1315000
0*
#1320000
0X
b1111001 =
b1111001 E
b1111001 Y
1*
#1325000
0*
#1330000
1X
b11110010 =
b11110010 E
b11110010 Y
1*
#1335000
0*
#1340000
11
1-
b11100101 =
b11100101 E
b11100101 Y
1*
#1345000
0*
#1350000
0-
b11001011 =
b11001011 E
b11001011 Y
1N
1"
b11100101 #
b11100101 :
b11100101 P
0'
1*
#1355000
0*
#1360000
0N
0"
b10010111 =
b10010111 E
b10010111 Y
1*
#1365000
0*
#1370000
01
0X
b101111 =
b101111 E
b101111 Y
1'
1*
#1375000
0*
#1380000
b1011110 =
b1011110 E
b1011110 Y
1*
#1385000
0*
#1390000
b10111100 =
b10111100 E
b10111100 Y
1*
#1395000
0*
#1400000
11
1-
b1111000 =
b1111000 E
b1111000 Y
1*
#1405000
0*
#1410000
0-
1X
b11110000 =
b11110000 E
b11110000 Y
1N
1"
b1111000 #
b1111000 :
b1111000 P
0'
1*
#1415000
0*
#1420000
0X
0N
0"
b11100001 =
b11100001 E
b11100001 Y
1*
#1425000
0*
#1430000
01
1X
b11000010 =
b11000010 E
b11000010 Y
1'
1*
#1435000
0*
#1440000
0X
b10000101 =
b10000101 E
b10000101 Y
1*
#1445000
0*
#1450000
b1010 =
b1010 E
b1010 Y
1*
#1455000
0*
#1460000
11
1-
b10100 =
b10100 E
b10100 Y
1*
#1465000
0*
#1470000
0-
1X
b101000 =
b101000 E
b101000 Y
1N
1"
b10100 #
b10100 :
b10100 P
0'
1*
#1475000
0*
#1480000
0N
0"
b1010001 =
b1010001 E
b1010001 Y
1*
#1485000
0*
#1490000
0X
b10100011 =
b10100011 E
b10100011 Y
1'
1*
#1490001
14
0+
01
b0 ,
b0 5
b0 B
b0 2
b0 7
b0 D
#1495000
0*
#1500000
0>
b0 8
b0 R
b0 V
b0 9
b0 Q
b0 U
b0 ?
b0 M
0!
0&
b0 #
b0 :
b0 P
0'
b11001 =
b11001 E
b11001 Y
1*
#1505000
0*
#1510000
1*
#1510001
04
1+
#1515000
0*
#1520000
1!
1&
1'
1*
#1525000
0*
#1530000
1*
#1535000
0*
#1540000
1*
#1545000
0*
#1550000
10
13
1/
1*
#1555000
0*
#1560000
03
0/
b1 T
0!
0&
1*
#1565000
0*
#1570000
b10 T
1$
1*
#1575000
0*
#1580000
b0 T
0$
1*
#1585000
0*
#1590000
00
1!
1&
1*
#1595000
0*
#1600000
10
13
b1011010 2
b1011010 7
b1011010 D
1/
b100 .
b100 6
b100 C
1*
#1605000
0*
#1610000
03
0/
b1 T
0!
0&
b100 S
1*
#1615000
0*
#1620000
b10 T
1$
b1011010 9
b1011010 Q
b1011010 U
1*
#1625000
0*
#1630000
b0 T
0$
1*
#1635000
0*
#1640000
00
1!
1&
1*
#1645000
0*
#1650000
10
13
b10001110 2
b10001110 7
b10001110 D
1/
b1000 .
b1000 6
b1000 C
1*
#1655000
0*
#1660000
03
0/
b1 T
0!
0&
b1000 S
1*
#1665000
0*
#1670000
1X
b10 T
1$
b10001110 8
b10001110 R
b10001110 V
1*
#1675000
0*
#1680000
b0 T
0$
1*
#1685000
0*
#1690000
00
1!
1&
1*
#1695000
0*
#1700000
10
13
b10 2
b10 7
b10 D
1/
b0 .
b0 6
b0 C
1*
#1705000
0*
#1710000
03
0/
b1 T
0!
0&
b0 S
1*
#1715000
0*
#1720000
1<
b10 T
1$
b10 ?
b10 M
1*
#1725000
0*
#1730000
0X
b1011010 =
b1011010 E
b1011010 Y
b0 T
0$
1*
#1735000
0*
#1740000
00
1!
1&
1*
#1745000
0*
#1750000
1*
#1755000
0*
#1760000
1*
#1765000
0*
#1770000
10
13
b1 2
b1 7
b1 D
1/
1*
#1775000
0*
#1780000
03
0/
b1 T
0!
0&
1*
#1785000
0*
#1790000
0<
1>
b10 T
1$
b1 ?
b1 M
1*
#1795000
0*
#1800000
b0 T
0$
b10110100 =
b10110100 E
b10110100 Y
1*
#1805000
0*
#1810000
00
1X
b1101000 =
b1101000 E
b1101000 Y
1!
1&
1*
#1815000
0*
#1820000
b11010001 =
b11010001 E
b11010001 Y
1*
#1825000
0*
#1830000
0X
b10100011 =
b10100011 E
b10100011 Y
1*
#1835000
0*
#1840000
11
1-
b1100 ,
b1100 5
b1100 B
b1000110 =
b1000110 E
b1000110 Y
1*
#1845000
0*
#1850000
0-
1X
b10001100 =
b10001100 E
b10001100 Y
1N
1"
b1000110 #
b1000110 :
b1000110 P
0'
1*
#1855000
0*
#1860000
0N
0"
b11001 =
b11001 E
b11001 Y
1*
#1865000
0*
#1870000
01
b110011 =
b110011 E
b110011 Y
1'
1*
#1875000
0*
#1880000
0X
b1100111 =
b1100111 E
b1100111 Y
1*
#1885000
0*
#1890000
b11001110 =
b11001110 E
b11001110 Y
1*
#1895000
0*
#1900000
11
1-
1X
b10011100 =
b10011100 E
b10011100 Y
1*
#1905000
0*
#1910000
0-
b111001 =
b111001 E
b111001 Y
1N
1"
b10011100 #
b10011100 :
b10011100 P
0'
1*
#1915000
0*
#1920000
0N
0"
b1110011 =
b1110011 E
b1110011 Y
1*
#1925000
0*
#1930000
01
b11100111 =
b11100111 E
b11100111 Y
1'
1*
#1935000
0*
#1940000
0X
b11001111 =
b11001111 E
b11001111 Y
1*
#1945000
0*
#1950000
b10011110 =
b10011110 E
b10011110 Y
1*
#1955000
0*
#1960000
11
1-
b111100 =
b111100 E
b111100 Y
1*
#1965000
0*
#1970000
0-
1X
b1111000 =
b1111000 E
b1111000 Y
1N
1"
b111100 #
b111100 :
b111100 P
0'
1*
#1975000
0*
#1980000
0N
0"
b11110001 =
b11110001 E
b11110001 Y
1*
#1985000
0*
#1990000
01
0X
b11100011 =
b11100011 E
b11100011 Y
1'
1*
#1995000
0*
#2000000
1X
b11000110 =
b11000110 E
b11000110 Y
1*
#2005000
0*
#2010000
b10001101 =
b10001101 E
b10001101 Y
1*
#2015000
0*
#2020000
11
1-
0X
b11011 =
b11011 E
b11011 Y
1*
#2025000
0*
#2030000
0-
b110110 =
b110110 E
b110110 Y
1N
1"
b11011 #
b11011 :
b11011 P
0'
1*
#2035000
0*
#2040000
0N
0"
b1101100 =
b1101100 E
b1101100 Y
1*
#2045000
0*
#2050000
01
b11011000 =
b11011000 E
b11011000 Y
1'
1*
#2055000
0*
#2060000
1X
b10110000 =
b10110000 E
b10110000 Y
1*
#2065000
0*
#2070000
0X
b1100001 =
b1100001 E
b1100001 Y
1*
#2075000
0*
#2080000
11
1-
b11000010 =
b11000010 E
b11000010 Y
1*
#2085000
0*
#2090000
0-
b10000100 =
b10000100 E
b10000100 Y
1N
1"
b11000010 #
b11000010 :
b11000010 P
0'
1*
#2095000
0*
#2100000
1X
0N
0"
b1000 =
b1000 E
b1000 Y
1*
#2105000
0*
#2110000
01
0X
b10001 =
b10001 E
b10001 Y
1'
1*
#2115000
0*
#2120000
11
1-
1X
b100010 =
b100010 E
b100010 Y
1*
#2125000
0*
